pylint_forbidden_imports/__init__.py
pylint_forbidden_imports/encapsulated_modules.py
pylint_forbidden_imports/forbidden_imports.py
pylint_forbidden_imports/modules.py
pylint_forbidden_imports-1.0.0.dist-info/LICENSE
pylint_forbidden_imports-1.0.0.dist-info/METADATA
pylint_forbidden_imports-1.0.0.dist-info/WHEEL
pylint_forbidden_imports-1.0.0.dist-info/top_level.txt
pylint_forbidden_imports-1.0.0.dist-info/RECORD
