Metadata-Version: 2.1
Name: pylint-forbidden-imports
Version: 1.0.0
Summary: Plugin for PyLint that checks if we import from permitted modules
Home-page: https://github.com/Enforcer/pylint_forbidden_imports
Author: Sebastian Buczyński
License: UNKNOWN
Download-URL: https://github.com/Enforcer/pylint_forbidden_imports/archive/1.0.0.tar.gz
Keywords: pylint,imports
Platform: UNKNOWN
Provides-Extra: dev
Requires-Dist: pytest ; extra == 'dev'
Requires-Dist: black ; extra == 'dev'
Requires-Dist: pylint ; extra == 'dev'
